README
setup.py
g8core/__init__.py
g8core/client.py
g8core/typchk.py
g8core.egg-info/PKG-INFO
g8core.egg-info/SOURCES.txt
g8core.egg-info/dependency_links.txt
g8core.egg-info/requires.txt
g8core.egg-info/top_level.txt