Metadata-Version: 1.0
Name: g8core
Version: 1.0.0
Summary: G8OS cores client
Home-page: https://github.com/g8os/core0
Author: Muhamad Azmy
Author-email: muhamada@greenitglobe.com
License: Apache 2.0
Platform: UNKNOWN
